{
  "tasks": [
    {
      "id": "lqjrx855",
      "title": "Добавить юнит тесты",
      "description": "Покрыть приложение юнит тестами",
      "created": "2023-12-24T17:39:03.929Z",
      "status": "done"
    },
    {
      "id": "lshidz38",
      "title": "Исправить значок 'Сохранить' ",
      "description": "Иконка в компоненте \"Сохранить\" теперь не работает, нам нужно это исправить",
      "created": "2024-02-11T12:56:01.508Z",
      "status": "done"
    },
    {
      "id": "lshie1m2",
      "title": "Добавить раздел пользователя в настройки",
      "description": "В настройках должен быть раздел пользователя, где пользователи могут редактировать данные своего профиля: имя, телефон, адрес электронной почты и т. д.",
      "created": "2024-02-11T12:56:04.778Z",
      "status": "inProgress"
    },
    {
      "id": "lshie9w9",
      "title": "Что-то сделать",
      "description": "",
      "created": "2024-02-11T12:56:15.513Z",
      "status": "backlog"
    },
    {
      "id": "lshieb91",
      "title": "Что-то пофиксить",
      "description": "",
      "created": "2024-02-11T12:56:17.269Z",
      "status": "ready"
    },
    {
      "id": "lshjoyjv",
      "title": "Что-то не сделать",
      "description": "",
      "created": "2024-02-11T13:32:33.642Z",
      "status": "inProgress"
    },
    {
      "id": "ltd49s8w",
      "title": "екн64нг",
      "description": "",
      "created": "2024-03-04T15:49:29.024Z",
      "status": "ready"
    },
    {
      "id": "ltd5rdk3",
      "title": "ек",
      "description": "",
      "created": "2024-03-04T16:31:09.410Z",
      "status": "ready"
    },
    {
      "id": "ltd6hbgn",
      "title": "у3",
      "description": "",
      "created": "2024-03-04T16:51:19.751Z",
      "status": "backlog"
    },
    {
      "id": "ltd8q5zo",
      "title": "1",
      "description": "",
      "created": "2024-03-04T17:54:11.796Z",
      "status": "backlog"
    },
    {
      "id": "ltd8q9xn",
      "title": "4",
      "description": "",
      "created": "2024-03-04T17:54:16.907Z",
      "status": "backlog"
    },
    {
      "id": "lte3kwpy",
      "title": "некн",
      "description": "",
      "created": "2024-03-05T08:17:54.598Z",
      "status": "backlog"
    },
    {
      "id": "lte5jvmd",
      "title": "уу",
      "description": "",
      "created": "2024-03-05T09:13:05.749Z",
      "status": "backlog"
    },
    {
      "id": "lte5mpdu",
      "title": "6yut",
      "description": "",
      "created": "2024-03-05T09:15:17.634Z",
      "status": "backlog"
    }
  ]
}